LICENSE
README.md
setup.py
hausnet_heartbeat_client.egg-info/PKG-INFO
hausnet_heartbeat_client.egg-info/SOURCES.txt
hausnet_heartbeat_client.egg-info/dependency_links.txt
hausnet_heartbeat_client.egg-info/requires.txt
hausnet_heartbeat_client.egg-info/top_level.txt
heartbeat_client/__init__.py
heartbeat_client/client.py