Metadata-Version: 2.1
Name: hausnet-heartbeat-client
Version: 0.1.1
Summary: A client for the Heartbeat monitoring service
Home-page: https://github.com/HausNet/heartbeat-client
Author: HausNet Developers
Author-email: dev@hausnet.io
License: UNKNOWN
Platform: UNKNOWN
Classifier: Programming Language :: Python :: 3
Classifier: License :: OSI Approved :: MIT License
Classifier: Operating System :: OS Independent
Requires-Python: >=3.9
License-File: LICENSE
